drudge_parser.py
drudge_parser-3.0.2.dist-info/DESCRIPTION.rst
drudge_parser-3.0.2.dist-info/METADATA
drudge_parser-3.0.2.dist-info/RECORD
drudge_parser-3.0.2.dist-info/WHEEL
drudge_parser-3.0.2.dist-info/metadata.json
drudge_parser-3.0.2.dist-info/top_level.txt
