Metadata-Version: 2.0
Name: drudge-parser
Version: 3.0.2
Summary: Naive parser for the Drudge Report
Home-page: https://github.com/mrasband/drudge_parser
Author: Matt Rasband
Author-email: matt.rasband@gmail.com
License: MIT
Download-URL: https://github.com/mrasband/drudge_parser/archive/v3.0.2.tar.gz
Keywords: parsing,webscraping,drudge,drudgereport
Platform: UNKNOWN
Classifier: Programming Language :: Python :: 2.6
Classifier: Programming Language :: Python :: 2.7
Classifier: Programming Language :: Python :: 3.3
Classifier: Programming Language :: Python :: 3.4
Classifier: Programming Language :: Python :: 3.5
Classifier: License :: OSI Approved :: MIT License
Classifier: Intended Audience :: Developers
Classifier: Development Status :: 4 - Beta
